{
  "manifestVersion": "3.2",
  "proxies": [
    {
      "address": "0xB1d04ECd752A5F15848CAA5035c74f601f572734",
      "txHash": "0xf7387b8bd65d5c3fe210052641bf86ebd4d9a523b7e65733187f6620ac6a20fb",
      "kind": "transparent"
    }
  ],
  "impls": {
    "472c056c09b2c2bba804837b8870cf765e7f0273c13567127dba807fe19ed08f": {
      "address": "0x6f1472D2f258D0D2D139e3A4D83189c593953Cd6",
      "txHash": "0x2e30c17eadcffc79ddcd303bce35372774655b83a1c52a5f5c889d01fbf012fe",
      "layout": {
        "solcVersion": "0.8.20",
        "storage": [
          {
            "label": "message",
            "offset": 0,
            "slot": "0",
            "type": "t_string_storage",
            "contract": "Swisstronik",
            "src": "contracts/Hello_swtr.sol:5"
          }
        ],
        "types": {
          "t_string_storage": {
            "label": "string",
            "numberOfBytes": "32"
          }
        },
        "namespaces": {}
      }
    }
  }
}
